{
  "project_info": {
    "project_number": "509022153033",
    "project_id": "mbtigroup-4b280",
    "storage_bucket": "mbtigroup-4b280.firebasestorage.app"
  },
  "client": [
    {
      "client_info": {
        "mobilesdk_app_id": "1:509022153033:android:314eb62343b43a9196d298",
        "android_client_info": {
          "package_name": "com.MBTIGroup.app"
        }
      },
      "oauth_client": [],
      "api_key": [
        {
          "current_key": "AIzaSyCz0o_GsUmvT6iny1EMIzVFZsIxParfuwM"
        }
      ],
      "services": {
        "appinvite_service": {
          "other_platform_oauth_client": []
        }
      }
    },
    {
      "client_info": {
        "mobilesdk_app_id": "1:509022153033:android:5cbdf65d80cd776496d298",
        "android_client_info": {
          "package_name": "com.example.nazokake"
        }
      },
      "oauth_client": [],
      "api_key": [
        {
          "current_key": "AIzaSyCz0o_GsUmvT6iny1EMIzVFZsIxParfuwM"
        }
      ],
      "services": {
        "appinvite_service": {
          "other_platform_oauth_client": []
        }
      }
    },
    {
      "client_info": {
        "mobilesdk_app_id": "1:509022153033:android:0fa1d3c7d33bb07896d298",
        "android_client_info": {
          "package_name": "com.mbtigroup.app"
        }
      },
      "oauth_client": [],
      "api_key": [
        {
          "current_key": "AIzaSyCz0o_GsUmvT6iny1EMIzVFZsIxParfuwM"
        }
      ],
      "services": {
        "appinvite_service": {
          "other_platform_oauth_client": []
        }
      }
    },
    {
      "client_info": {
        "mobilesdk_app_id": "1:509022153033:android:476ce118fce0915a96d298",
        "android_client_info": {
          "package_name": "com.mbtigroup.myapp"
        }
      },
      "oauth_client": [],
      "api_key": [
        {
          "current_key": "AIzaSyCz0o_GsUmvT6iny1EMIzVFZsIxParfuwM"
        }
      ],
      "services": {
        "appinvite_service": {
          "other_platform_oauth_client": []
        }
      }
    },
    {
      "client_info": {
        "mobilesdk_app_id": "1:509022153033:android:0d99bdc4345a9e3d96d298",
        "android_client_info": {
          "package_name": "com.mystudy.study_flutter_firebase"
        }
      },
      "oauth_client": [],
      "api_key": [
        {
          "current_key": "AIzaSyCz0o_GsUmvT6iny1EMIzVFZsIxParfuwM"
        }
      ],
      "services": {
        "appinvite_service": {
          "other_platform_oauth_client": []
        }
      }
    }
  ],
  "configuration_version": "1"
}